easy_ernie/__init__.py
easy_ernie/auxiliary.py
easy_ernie/ernie.py
easy_ernie/fast_ernie.py
easy_ernie/model.py
easy_ernie-1.0.1.dist-info/LICENSE
easy_ernie-1.0.1.dist-info/METADATA
easy_ernie-1.0.1.dist-info/WHEEL
easy_ernie-1.0.1.dist-info/top_level.txt
easy_ernie-1.0.1.dist-info/RECORD
