Metadata-Version: 2.1
Name: easy-ernie
Version: 1.0.1
Summary: 简洁的调用文心一言的WebAPI
Home-page: https://github.com/XiaoXinYo/Easy-Ernie
Author: XiaoXinYo
License: MIT
Classifier: License :: OSI Approved :: MIT License
Classifier: Operating System :: OS Independent
Classifier: Intended Audience :: Developers
Classifier: Programming Language :: Python :: 3.8
Classifier: Programming Language :: Python :: 3.9
Classifier: Programming Language :: Python :: 3.10
Classifier: Programming Language :: Python :: 3.11
Classifier: Programming Language :: Python :: 3.12
Requires-Python: >=3.8
License-File: LICENSE
Requires-Dist: requests
